keble_chains/__init__.py
keble_chains/chainables/__init__.py
keble_chains/chainables/chunk/__init__.py
keble_chains/chainables/chunk/chainable.py
keble_chains/chainables/metadata/__init__.py
keble_chains/chainables/metadata/chainable.py
keble_chains/chainables/prune/__init__.py
keble_chains/chainables/prune/chainable.py
keble_chains/chains.py
keble_chains/exceptions/__init__.py
keble_chains/exceptions/openai.py
keble_chains/export/__init__.py
keble_chains/export/export.py
keble_chains/interact/__init__.py
keble_chains/interact/ai/__init__.py
keble_chains/interact/ai/azure.py
keble_chains/interact/ai/fake.py
keble_chains/interact/ai/session.py
keble_chains/interact/ai/token_manager.py
keble_chains/interact/m14/__init__.py
keble_chains/interact/m14/m14_compressors.py
keble_chains/interact/m14/m14_session.py
keble_chains/template/__init__.py
keble_chains/template/base.py
keble_chains/template/chat.py
keble_chains/template/email.py
keble_chains/template/openai.py
keble_chains/tuning/__init__.py
keble_chains/tuning/datasets.py
keble_chains/typings/__init__.py
keble_chains/typings/abc.py
keble_chains/typings/ai.py
keble_chains/typings/collected.py
keble_chains/typings/dataset.py
keble_chains/typings/export.py
keble_chains/typings/main.py
keble_chains/typings/valid.py
keble_chains/utils/__init__.py
keble_chains/utils/main.py
keble_chains-0.0.8.dist-info/LICENSE
keble_chains-0.0.8.dist-info/METADATA
keble_chains-0.0.8.dist-info/WHEEL
keble_chains-0.0.8.dist-info/RECORD
