Metadata-Version: 2.1
Name: keble-chains
Version: 0.0.8
Summary: Keble ai model toolkit
Author: zhenhao-ma
Author-email: bob0103779@gmail.com
Requires-Python: >=3.10,<4.0
Classifier: Programming Language :: Python :: 3
Classifier: Programming Language :: Python :: 3.10
Classifier: Programming Language :: Python :: 3.11
Classifier: Programming Language :: Python :: 3.12
Requires-Dist: jsonlines (>=4.0.0,<5.0.0)
Requires-Dist: keble-db (>=0,<1)
Requires-Dist: keble-helpers (>=0,<1)
Requires-Dist: langchain-openai (>=0.0.2.post1,<0.0.3)
Requires-Dist: openai (>=1.8.0,<2.0.0)
Requires-Dist: partialjson (>=0.0.5,<0.0.6)
Requires-Dist: pydantic (>=2.3.0,<3.0.0)
Requires-Dist: pymongo (>=4.5.0,<5.0.0)
Requires-Dist: qdrant-client (>=1.7.0,<2.0.0)
Requires-Dist: redis (>=5.0.0,<6.0.0)
Requires-Dist: sqlmodel (>=0.0.14,<0.0.15)
Requires-Dist: tiktoken (>=0.5.2,<0.6.0)
